tradingview_ta_v2/__init__.py
tradingview_ta_v2/main.py
tradingview_ta_v2/technicals.py
tradingview_ta_v2-1.0.0.dist-info/LICENSE
tradingview_ta_v2-1.0.0.dist-info/METADATA
tradingview_ta_v2-1.0.0.dist-info/WHEEL
tradingview_ta_v2-1.0.0.dist-info/top_level.txt
tradingview_ta_v2-1.0.0.dist-info/RECORD
