Metadata-Version: 2.1
Name: tradingview_ta_v2
Version: 1.0.0
Summary: Unofficial TradingView technical analysis API wrapper.
Home-page: https://github.com/codingfordummies911/tradingview-ta-v2
Author: codingfordummies911
Author-email: codingfordummies911@gmail.com
Project-URL: Demo, https://tradingview.brianthe.dev
Project-URL: Documentation, https://python-tradingview-ta.readthedocs.io
Project-URL: Source, https://github.com/codingfordummies911/tradingview-ta-v2
Classifier: Programming Language :: Python :: 3
Classifier: License :: OSI Approved :: MIT License
Classifier: Operating System :: OS Independent
Requires-Python: >=3.6
License-File: LICENSE
Requires-Dist: requests
